attribench/__init__.py
attribench/_activation_fns.py
attribench/_attribution_method.py
attribench/_method_factory.py
attribench/_model_factory.py
attribench/_segmentation.py
attribench/_stat.py
attribench/data/__init__.py
attribench/data/_index_dataset.py
attribench/data/_typing.py
attribench/data/attributions_dataset/__init__.py
attribench/data/attributions_dataset/_attributions_dataset.py
attribench/data/attributions_dataset/_attributions_dataset_writer.py
attribench/data/hdf5_dataset/__init__.py
attribench/data/hdf5_dataset/_hdf5_dataset.py
attribench/data/hdf5_dataset/_hdf5_dataset_writer.py
attribench/data/nd_array_tree/__init__.py
attribench/data/nd_array_tree/_nd_array_tree.py
attribench/data/nd_array_tree/_random_access_nd_array_tree.py
attribench/distributed/__init__.py
attribench/distributed/_compute_attributions.py
attribench/distributed/_distributed_computation.py
attribench/distributed/_distributed_sampler.py
attribench/distributed/_message.py
attribench/distributed/_select_samples.py
attribench/distributed/_train_adversarial_patches.py
attribench/distributed/_worker.py
attribench/distributed/metrics/__init__.py
attribench/distributed/metrics/_metric.py
attribench/distributed/metrics/_metric_worker.py
attribench/distributed/metrics/deletion/__init__.py
attribench/distributed/metrics/deletion/_deletion.py
attribench/distributed/metrics/deletion/_deletion_worker.py
attribench/distributed/metrics/impact_coverage/__init__.py
attribench/distributed/metrics/impact_coverage/_impact_coverage.py
attribench/distributed/metrics/impact_coverage/_impact_coverage_worker.py
attribench/distributed/metrics/infidelity/__init__.py
attribench/distributed/metrics/infidelity/_infidelity.py
attribench/distributed/metrics/infidelity/_infidelity_worker.py
attribench/distributed/metrics/insertion/__init__.py
attribench/distributed/metrics/insertion/_insertion.py
attribench/distributed/metrics/irof/__init__.py
attribench/distributed/metrics/irof/_irof.py
attribench-0.1.9.dist-info/LICENSE
attribench-0.1.9.dist-info/METADATA
attribench-0.1.9.dist-info/WHEEL
attribench-0.1.9.dist-info/top_level.txt
attribench-0.1.9.dist-info/RECORD
