Metadata-Version: 2.1
Name: attribench
Version: 0.1.9
Summary: A benchmark for feature attribution techniques
Author-email: Arne Gevaert <arne.gevaert@ugent.be>, Axel-Jan Rousseau <axeljan.rousseau@uhasselt.be>
License: MIT License
Project-URL: Homepage, https://github.com/arnegevaert/benchmark
Project-URL: Documentation, http://attribench.readthedocs.io/
Keywords: attributions,benchmark,explanation,machine learning
Classifier: Development Status :: 3 - Alpha
Classifier: License :: OSI Approved :: MIT License
Classifier: Programming Language :: Python
Classifier: Programming Language :: Python :: 3.10
Requires-Python: >=3.10
License-File: LICENSE
Requires-Dist: torch <2,>=1.5.0
Requires-Dist: torchvision >=0.14.0
Requires-Dist: krippendorff >=0.5.0
Requires-Dist: opencv-python >=4.7.0.0
Requires-Dist: scikit-learn >=1.2.0
Requires-Dist: scikit-image >=0.19.0
Requires-Dist: seaborn >=0.12.0
Requires-Dist: statsmodels >=0.14.0
Requires-Dist: h5py
Requires-Dist: tqdm
Requires-Dist: pyyaml
Provides-Extra: dev
Requires-Dist: bumpver ; extra == 'dev'
Requires-Dist: pytest ; extra == 'dev'
Provides-Extra: docs
Requires-Dist: sphinx ; extra == 'docs'
Requires-Dist: sphinx-rtd-theme ; extra == 'docs'
Requires-Dist: numpydoc ; extra == 'docs'
Requires-Dist: sphinx-autodoc-typehints ; extra == 'docs'
Requires-Dist: nbsphinx ; extra == 'docs'
Requires-Dist: ipython ; extra == 'docs'
Requires-Dist: jupyter ; extra == 'docs'
Requires-Dist: ipywidgets ; extra == 'docs'
